typing_speed/__init__.py
typing_speed/typing_speed.py
typing_speed-1.0.0.dist-info/LICENSE
typing_speed-1.0.0.dist-info/METADATA
typing_speed-1.0.0.dist-info/WHEEL
typing_speed-1.0.0.dist-info/top_level.txt
typing_speed-1.0.0.dist-info/RECORD
